{"id": 76, "difficultyLevel": 1, "subjectType": "Earth_and_Space", "tossup_question": "19) EARTH AND SPACE  Which of the following terms best describes the albedo of a planet:", "tossup_isShortAns": false, "tossup_MCQoptions": "W) electromagnetic energy\nX) density\nY) reflectivity\nZ) absorption", "tossup_answer": "ANSWER: Y) REFLECTIVITY", "tossup_imageURL": null, "bonus_question": "19) EARTH AND SPACE  Which of the following is NOT true of what occurs during an equinox:", "bonus_isShortAns": false, "bonus_MCQoptions": "W) equal length of day and night except at the poles\nX) the Earth is not tilted with respect to the ecliptic\nY) the Sun is directly overhead at the equator\nZ) the Moon is directly overhead at the poles", "bonus_answer": "ANSWER: Z) THE MOON IS DIRECTLY OVERHEAD AT THE POLES", "bonus_image": null}