{"id": 70, "difficultyLevel": 1, "subjectType": "Earth_and_Space", "tossup_question": "21) EARTH AND SPACE  What is the primary elemental product of stellar hydrogen fusion? ", "tossup_isShortAns": true, "tossup_MCQoptions": null, "tossup_answer": "ANSWER: HELIUM  ", "tossup_imageURL": null, "bonus_question": "21) EARTH AND SPACE  In the equatorial celestial coordinate system, what terms are synonymous with longitude and latitude, respectively? ", "bonus_isShortAns": true, "bonus_MCQoptions": null, "bonus_answer": "ANSWER: LONGITUDE = RIGHT ASCENSION; LATITUDE = DECLINATION ", "bonus_image": null}