{"id": 86, "difficultyLevel": 1, "subjectType": "Earth_and_Space", "tossup_question": "11) EARTH AND SPACE  What are called seismic shock waves that come before an earthquake called?", "tossup_isShortAns": true, "tossup_MCQoptions": null, "tossup_answer": "ANSWER: Foreshocks", "tossup_imageURL": null, "bonus_question": "11) EARTH AND SPACE  What red dwarf exists in the center of Alpha Centauri?  ", "bonus_isShortAns": true, "bonus_MCQoptions": null, "bonus_answer": "ANSWER: Alpha Proxima", "bonus_image": null}