{"id": 33, "difficultyLevel": 1, "subjectType": "Physics", "tossup_question": " -   \u2013  What type of radiation, also known as braking radiation, is emitted whenever a charged particle is deflected by another charged particle?", "tossup_isShortAns": true, "tossup_MCQoptions": null, "tossup_answer": "ANSWER: BREMSSTRAHLUNG RADIATION", "tossup_imageURL": null, "bonus_question": " -   \u2013  A 75 gram piece of copper is heated to 315 degrees Celsius and dropped into a beaker containing 220 milliliters of water that is at an initial temperature of 18 degrees Celsius. Which of the following temperatures, in degrees Celsius, is closest to the point at which the system is at equilibrium?", "bonus_isShortAns": false, "bonus_MCQoptions": "W) 5\nX) 25\nY) 60\nZ) 115", "bonus_answer": "ANSWER: X) 25", "bonus_image": null}